maxray/__init__.py
maxray/__main__.py
maxray/_test_module/__init__.py
maxray/_test_module/__main__.py
maxray/function_store.py
maxray/inators/base.py
maxray/inators/callgraph.py
maxray/inators/capture.py
maxray/inators/core.py
maxray/inators/display.py
maxray/inators/livegrep.py
maxray/inators/progress.py
maxray/inators/rerun.py
maxray/inators/template.py
maxray/logging.py
maxray/nodes.py
maxray/reprs.py
maxray/runner/__init__.py
maxray/runner/__main__.py
maxray/runner/exec_sources.py
maxray/transforms.py
maxray-0.7.0.dist-info/METADATA
maxray-0.7.0.dist-info/WHEEL
maxray-0.7.0.dist-info/entry_points.txt
maxray-0.7.0.dist-info/RECORD
