Metadata-Version: 2.1
Name: maxray
Version: 0.7.0
Summary: 
Author: blepabyte
Author-email: 255@blepabyte.me
Requires-Python: >=3.11,<4.0
Classifier: Programming Language :: Python :: 3
Classifier: Programming Language :: Python :: 3.11
Classifier: Programming Language :: Python :: 3.12
Requires-Dist: click (>=8.1.7,<9.0.0)
Requires-Dist: loguru (>=0.7.2,<0.8.0)
Requires-Dist: pyarrow (>=16.1.0,<17.0.0)
Requires-Dist: result (>=0.16.1,<0.17.0)
Requires-Dist: rich (>=13.7.1,<14.0.0)
Requires-Dist: watchfiles (>=0.22.0,<0.23.0)
Project-URL: Homepage, https://github.com/blepabyte/maxray
Project-URL: Source, https://github.com/blepabyte/maxray
Project-URL: Tracker, https://github.com/blepabyte/maxray/issues
